pybcodata/__init__.py
pybcodata/py.typed
pybcodata/query.py
pybcodata/session.py
pybcodata/shortcuts.py
pybcodata-0.1.0.dist-info/METADATA
pybcodata-0.1.0.dist-info/WHEEL
pybcodata-0.1.0.dist-info/licenses/LICENSE
pybcodata-0.1.0.dist-info/RECORD
