Metadata-Version: 2.4
Name: pybcodata
Version: 0.1.0
Summary: A Python client library for interacting with Business Central's OData API
Author-email: Akshay Prabhu <akshay.pra26@gmail.com>
License-Expression: MIT
License-File: LICENSE
Requires-Python: >=3.12
Requires-Dist: aiolimiter>=1.2.1
Requires-Dist: httpx>=0.24.0
Requires-Dist: loguru>=0.7.3
Requires-Dist: polars>=0.20.0
